LICENSE
README.md
pyproject.toml
setup.py
aftk/__init__.pxd
aftk/__init__.py
aftk.egg-info/PKG-INFO
aftk.egg-info/SOURCES.txt
aftk.egg-info/dependency_links.txt
aftk.egg-info/requires.txt
aftk.egg-info/top_level.txt
aftk/mathtools/__init__.pxd
aftk/mathtools/__init__.py
aftk/mathtools/psdm.c
aftk/mathtools/psdm.pxd
aftk/mathtools/psdm.pyi
aftk/mathtools/psdm.pyx
aftk/mathtools/sphankel.c
aftk/mathtools/sphankel.pxd
aftk/mathtools/sphankel.pyi
aftk/mathtools/sphankel.pyx
aftk/mathtools/spharm.c
aftk/mathtools/spharm.pxd
aftk/mathtools/spharm.pyi
aftk/mathtools/spharm.pyx